TimeQuery/__init__.py
TimeQuery-1.0.0.dist-info/LICENSE.txt
TimeQuery-1.0.0.dist-info/METADATA
TimeQuery-1.0.0.dist-info/WHEEL
TimeQuery-1.0.0.dist-info/top_level.txt
TimeQuery-1.0.0.dist-info/RECORD
