Metadata-Version: 2.1
Name: TimeQuery
Version: 1.0.0
Summary: Gets the time from specific locations.
Author: Pigeon Nation
License: MIT
Classifier: Programming Language :: Python :: 3
Classifier: License :: OSI Approved :: MIT License
Classifier: Operating System :: OS Independent
Classifier: Topic :: Other/Nonlisted Topic
License-File: LICENSE.txt
